abcfold/__init__.py
abcfold/abcfold.py
abcfold/argparse_utils.py
abcfold/backend_envs.py
abcfold/alphafold3/check_install.py
abcfold/alphafold3/run_alphafold3.py
abcfold/boltz/af3_to_boltz.py
abcfold/boltz/check_install.py
abcfold/boltz/run_boltz.py
abcfold/chai1/af3_to_chai.py
abcfold/chai1/chai.py
abcfold/chai1/check_install.py
abcfold/chai1/run_chai1.py
abcfold/data/config.ini
abcfold/html/abcfold.html.jinja2
abcfold/html/abcfold_vue.js
abcfold/html/bootstrap.css
abcfold/html/feature-viewer.bundle.js
abcfold/html/html_utils.py
abcfold/html/index.css
abcfold/html/jquery.js
abcfold/html/lodash.min.js
abcfold/html/style.css
abcfold/html/vue.min.js
abcfold/html/static/ABCfold-logo.svg
abcfold/html/static/favicon.svg
abcfold/html/static/main_page_example.png
abcfold/html/static/pae_viewer_example.png
abcfold/output/alphafold3.py
abcfold/output/atoms.py
abcfold/output/boltz.py
abcfold/output/chai.py
abcfold/output/file_handlers.py
abcfold/output/protenix.py
abcfold/output/utils.py
abcfold/plots/pae_plot.py
abcfold/plots/plddt_plot.py
abcfold/plots/pae-viewer-main/src/jsonify_scores.py
abcfold/plots/pae-viewer-main/src/css/complex-sequence-viewer.css
abcfold/plots/pae-viewer-main/src/css/pae-viewer.css
abcfold/plots/pae-viewer-main/src/css/structure-carousel.css
abcfold/plots/pae-viewer-main/src/css/structure-panel.css
abcfold/plots/pae-viewer-main/src/css/structure-viewer.css
abcfold/plots/pae-viewer-main/src/img/bootstrap-icons/arrows-fullscreen.svg
abcfold/plots/pae-viewer-main/src/img/bootstrap-icons/camera.svg
abcfold/plots/pae-viewer-main/src/img/bootstrap-icons/download.svg
abcfold/plots/pae-viewer-main/src/img/bootstrap-icons/exclamation-circle.svg
abcfold/plots/pae-viewer-main/src/img/bootstrap-icons/fullscreen-exit.svg
abcfold/plots/pae-viewer-main/src/img/bootstrap-icons/question-circle.svg
abcfold/plots/pae-viewer-main/src/img/pae-demo/favicon.svg
abcfold/plots/pae-viewer-main/src/img/pae-demo/screenshot-pae-viewer-overlapping-selection.png
abcfold-1.1.0.dist-info/METADATA
abcfold-1.1.0.dist-info/WHEEL
abcfold-1.1.0.dist-info/entry_points.txt
abcfold-1.1.0.dist-info/top_level.txt
abcfold-1.1.0.dist-info/RECORD
