Metadata-Version: 2.1
Name: abcfold
Version: 1.1.0
Summary: Input processing tools for AlphaFold3, Boltz, Chai-1 and Protenix
Author-email: Adam Simpkin <hlasimpk@liverpool.ac.uk>, Luc Elliott <hllelli2@liverpool.ac.uk>
License: BSD License
Project-URL: homepage, https://github.com/rigdenlab/ABCFold
Classifier: Development Status :: 4 - Beta
Classifier: Intended Audience :: Science/Research
Classifier: License :: OSI Approved :: BSD License
Classifier: Operating System :: OS Independent
Classifier: Programming Language :: Python
Classifier: Programming Language :: Python :: 3.10
Classifier: Programming Language :: Python :: 3.11
Classifier: Programming Language :: Python :: 3.12
Classifier: Topic :: Scientific/Engineering :: Bio-Informatics
Requires-Dist: numpy==1.26.4
Requires-Dist: colorama
Requires-Dist: tqdm
Requires-Dist: biopython==1.84
Requires-Dist: requests
Requires-Dist: types-requests
Requires-Dist: pandas==2.2.3
Requires-Dist: plotly
Requires-Dist: jinja2
Requires-Dist: pyarrow==19.0.1
